{
    "forge_marker": 1,
    "defaults": {

    },
    "variants": {
        "variant":{
            "palm_trees"     : {
                "textures": {
                    "end": "nord:blocks/wood/palm_trees/logTop",
                    "side": "nord:blocks/wood/palm_trees/log",
                    "all": "nord:blocks/wood/palm_trees/log",
                    "particle": "nord:blocks/wood/palm_trees/log"
                }
            },
            "orange"     : {
                "textures": {
                     "end": "nord:blocks/wood/orange/logTop",
                     "side": "nord:blocks/wood/orange/log",
                     "all": "nord:blocks/wood/orange/log",
                     "particle": "nord:blocks/wood/orange/log"
                }
            },
            "olive"     : {
                "textures": {
                    "end": "nord:blocks/wood/olive/logTop",
                    "side": "nord:blocks/wood/olive/log",
                    "all": "nord:blocks/wood/olive/log",
                    "particle": "nord:blocks/wood/olive/log"
                }
            },
            "mulberry"     : {
                "textures": {
                    "end": "nord:blocks/wood/mulberry/logTop",
                    "side": "nord:blocks/wood/mulberry/log",
                    "all": "nord:blocks/wood/mulberry/log",
                    "particle": "nord:blocks/wood/mulberry/log"
                }
            }
        },
        "axis":{
            "y":{
                 "model": "cube_column"
            },
            "z":{
                 "model": "column_side"
            },
            "x":{
                "model": "column_side",
                "y": 90
            },
            "none":{
                 "model": "cube_all"
            }
        }
    }
}